aiohttp_raw/__init__.py
aiohttp_raw/__version__.py
aiohttp_raw/client.py
aiohttp_raw/client_reqrep.py
aiohttp_raw-0.1.1.dist-info/LICENSE
aiohttp_raw-0.1.1.dist-info/METADATA
aiohttp_raw-0.1.1.dist-info/WHEEL
aiohttp_raw-0.1.1.dist-info/top_level.txt
aiohttp_raw-0.1.1.dist-info/RECORD
