Metadata-Version: 2.1
Name: aiohttp-raw
Version: 0.1.1
Summary: HTTP communication through raw sockets using aiohttp for RFC compliance testing
Home-page: https://github.com/realgam3/aiohttp-raw
Author: Tomer Zait (realgam3)
Author-email: realgam3@gmail.com
License: Apache 2.0
Project-URL: Source, https://github.com/realgam3/aiohttp-raw
Platform: any
Classifier: Environment :: Web Environment
Classifier: Development Status :: 5 - Production/Stable
Classifier: Intended Audience :: Developers
Classifier: Intended Audience :: Science/Research
Classifier: License :: OSI Approved :: Apache Software License
Classifier: Natural Language :: English
Classifier: Operating System :: OS Independent
Classifier: Programming Language :: Python
Classifier: Programming Language :: Python :: 3
Classifier: Programming Language :: Python :: 3.7
Classifier: Programming Language :: Python :: 3.8
Classifier: Programming Language :: Python :: 3.9
Classifier: Programming Language :: Python :: 3.10
Classifier: Programming Language :: Python :: 3.11
Classifier: Programming Language :: Python :: 3.12
Classifier: Programming Language :: Python :: 3 :: Only
Classifier: Programming Language :: Python :: Implementation :: CPython
Classifier: Programming Language :: Python :: Implementation :: PyPy
Classifier: Topic :: Internet :: WWW/HTTP
Classifier: Topic :: Software Development :: Libraries
Requires-Python: >=3.8
License-File: LICENSE
Requires-Dist: aiohttp>=3.9.1
Provides-Extra: socks
Requires-Dist: aiohttp-socks>=0.8.4; extra == "socks"
Provides-Extra: speedups
Provides-Extra: speedups-socks
Requires-Dist: aiohttp-socks>=0.8.4; extra == "speedups-socks"
Requires-Dist: brotlicffi>=1.1.0.0; platform_python_implementation != "CPython" and extra == "speedups-socks"
Requires-Dist: Brotli>=1.1.0; platform_python_implementation == "CPython" and extra == "speedups-socks"
Requires-Dist: aiodns>=1.1; (sys_platform == "linux" or sys_platform == "darwin") and extra == "speedups-socks"
Requires-Dist: brotlicffi>=1.1.0.0; platform_python_implementation != "CPython" and extra == "speedups"
Requires-Dist: Brotli>=1.1.0; platform_python_implementation == "CPython" and extra == "speedups"
Requires-Dist: aiodns>=1.1; (sys_platform == "linux" or sys_platform == "darwin") and extra == "speedups"
